Workbook

Sheet Data
A1: PVR INOX - reported operating metrics (public disclosures)
A2: Blue = hard-coded from company results as reported by the press (see Source). Black = formula.
A4: Metric | B4: Q4 FY25 | C4: Q4 FY26 | D4: YoY change | E4: FY26 | F4: Source / note
A5: Footfalls (million) | B5: 30.5 | C5: 31 | D5: =C5/B5-1 -> 0.016393443 | E5: 150 | F5: Q4: Business Standard / PVR INOX Q4 FY26 results, 11 May 2026. FY26: 150 mn admissions (+10% YoY).
A6: Average ticket price, ATP (Rs) | B6: 258 | C6: 315 | D6: =C6/B6-1 -> 0.22093023 | E6: 280 | F6: Q4 FY25 ATP derived from reported Q4 FY26 ATP and +22.4% YoY. FY26 ATP Rs 280 (+8%).
A7: F&B spend per head, SPH (Rs) | B7: 125 | C7: 165 | D7: =C7/B7-1 -> 0.32 | E7: 147 | F7: Q4 FY25 SPH from reported +32.3% YoY. FY26 SPH Rs 147 (+10%).
A8: Occupancy | B8: 0.205 | C8: 0.239 | D8: =C8/B8-1 -> 0.16585366 | F8: Business Standard (brokerage note), 12 May 2026.
A9: Box-office revenue (Rs Cr) | C9: 819 | F9: Q4 FY26 press coverage of results (DSIJ summary).
A10: F&B revenue (Rs Cr) | C10: 482 | F10: Same source.
A11: Advertising revenue (Rs Cr) | C11: 110 | F11: Same source.
A12: Reported revenue (Rs Cr) | B12: 1230 | C12: 1547 | D12: =C12/B12-1 -> 0.25772358 | F12: Q4 FY26 revenue Rs 1,547 Cr; Q4 FY25 Rs 1,230 Cr (Kotak Neo / Business Standard).
A13: Screens (year-end) | E13: 1798 | F13: 1,798 screens, 359 cinemas, 113 cities; 93 added and 18 exited in FY26.
A15: Derived: net realisation (reported revenue / (footfalls x ATP or SPH))
A16: Box office net realisation, Q4 FY26 | C16: =C9/(C5*C6/10) -> 0.83870968 | F16: Insight: reported ATP/SPH are higher than revenue per head, consistent with ATP/SPH being quoted gross of GST (our inference, not a company statement).
A17: F&B net realisation, Q4 FY26 | C17: =C10/(C5*C7/10) -> 0.94232649

Sheet Revenue_Bridge
A1: What drove Q4 FY26 growth in revenue per audience (tickets + F&B, gross of tax)?
A3: Item | B3: Q4 FY25 | C3: Q4 FY26 | D3: Note
A4: Footfalls (mn) | B4: =Data!B5 -> 30.5 | C4: =Data!C5 -> 31
A5: ATP (Rs) | B5: =Data!B6 -> 258 | C5: =Data!C6 -> 315
A6: SPH (Rs) | B6: =Data!B7 -> 125 | C6: =Data!C7 -> 165
A7: Gross ticket + F&B value (Rs mn) = footfalls x (ATP+SPH) | B7: =B4*(B5+B6) -> 11681.5 | C7: =C4*(C5+C6) -> 14880
A9: Bridge (Rs mn) | B9: Rs mn | C9: Share of change
A10: Footfall effect (change in footfalls x old ATP+SPH) | B10: =(C4-B4)*(B5+B6) -> 191.5 | C10: =B10/$B$13 -> 0.059871815
A11: ATP effect (change in ATP x new footfalls) | B11: =(C5-B5)*C4 -> 1767 | C11: =B11/$B$13 -> 0.55244646
A12: SPH effect (change in SPH x new footfalls) | B12: =(C6-B6)*C4 -> 1240 | C12: =B12/$B$13 -> 0.38768173
A13: Total change | B13: =SUM(B10:B12) -> 3198.5 | C13: =SUM(C10:C12) -> 1
A14: Check vs direct difference (should be 0) | B14: =B13-(C7-B7) -> 0
A16: Share of growth from price and spend (ATP + SPH) | C16: =C11+C12 -> 0.94012819
A18: Reading: audience grew ~1.6% while ATP rose ~22% and SPH ~32%, so almost all growth came from charging/earning more per visitor. Q4 FY26 was also blockbuster-driven (the company credits a big film), so this is not guaranteed to repeat.

Sheet Pricing_Scenarios
A1: Should PVR INOX push price, F&B or footfalls? (annual FY26 base, per-patron economics)
A2: Blue = assumptions. Yellow = key assumptions NOT disclosed by PVR INOX; test them in the sensitivity table. This is an illustrative student model, not company guidance.
A4: Base footfalls (mn) | B4: =Data!E5 -> 150 | C4: FY26 reported.
A5: Base ATP (Rs) | B5: =Data!E6 -> 280 | C5: FY26 reported.
A6: Base SPH (Rs) | B6: =Data!E7 -> 147 | C6: FY26 reported.
A7: Box-office net realisation | B7: =Data!C16 -> 0.83870968 | C7: Derived from Q4 FY26 (assumed to hold for FY26).
A8: F&B net realisation | B8: =Data!C17 -> 0.94232649 | C8: Derived from Q4 FY26.
A9: Film distributor share of net box office | B9: 0.45 | C9: ASSUMPTION - not from PVR disclosures. Exhibitors typically share a large part of net box office with distributors; verify before relying. Tested below.
A10: F&B cost of goods (% of F&B revenue) | B10: 0.3 | C10: ASSUMPTION - not from PVR disclosures. Tested below.
A11: Scenario A: ATP increase (Rs) | B11: 10 | C11: Scenario lever.
A12: Scenario A: footfall change from price rise | B12: -0.03 | C12: ASSUMPTION (price elasticity). Tested below via break-even.
A13: Scenario B: SPH increase (combos, upsell) | B13: 0.08 | C13: Scenario lever.
A14: Scenario C: footfall growth (marketing, programming) | B14: 0.03 | C14: Scenario lever.
A16: Contribution per patron (Rs) = ATP x net box x (1 - distributor share) + SPH x net F&B x (1 - COGS)
A17: Base contribution per patron (Rs) | B17: =B5*B7*(1-B9)+B6*B8*(1-B10) -> 226.12669
A18: Base net revenue per patron (Rs) | B18: =B5*B7+B6*B8 -> 373.3607
A20: Scenario | B20: Footfalls (mn) | C20: Net revenue (Rs Cr) | D20: Change in net revenue (Rs Cr) | E20: Contribution (Rs Cr) | F20: Change in contribution (Rs Cr) | G20: Change %
A21: Base | B21: =B4 -> 150 | C21: =B21*B18/10 -> 5600.4106 | E21: =B21*B17/10 -> 3391.9003
A22: A. Raise ATP | B22: =B4*(1+B12) -> 145.5 | C22: =B22*((B5+B11)*B7+B6*B8)/10 -> 5554.4305 | D22: =C22-$C$21 -> -45.980059 | E22: =B22*((B5+B11)*B7*(1-B9)+B6*B8*(1-B10))/10 -> 3357.261 | F22: =E22-$E$21 -> -34.639267 | G22: =F22/$E$21 -> -0.010212348
A23: B. Lift F&B spend | B23: =B4 -> 150 | C23: =B23*(B5*B7+B6*(1+B13)*B8)/10 -> 5766.637 | D23: =C23-$C$21 -> 166.22639 | E23: =B23*(B5*B7*(1-B9)+B6*(1+B13)*B8*(1-B10))/10 -> 3508.2588 | F23: =E23-$E$21 -> 116.35848 | G23: =F23/$E$21 -> 0.034304804
A24: C. Grow footfalls | B24: =B4*(1+B14) -> 154.5 | C24: =B24*B18/10 -> 5768.4229 | D24: =C24-$C$21 -> 168.01232 | E24: =B24*B17/10 -> 3493.6573 | F24: =E24-$E$21 -> 101.75701 | G24: =F24/$E$21 -> 0.03
A26: Break-even: footfall drop that wipes out the contribution gain from the ATP rise | B26: =B17/((B5+B11)*B7*(1-B9)+B6*B8*(1-B10))-1 -> -0.019991815 | C26: If footfalls fall by more than this, raising ATP loses money (on contribution). Compare with the assumed footfall change.
A28: SENSITIVITY: change in contribution (Rs Cr) from +Rs 10 ATP (Scenario A), by distributor share and footfall change
A29: Distributor share -> / footfall change down | B29: 0.4 | C29: 0.45 | D29: 0.5
A30: -0.01 | B30: =$B$4*(1+$A30)*(($B$5+$B$11)*$B$7*(1-B$29)+$B$6*$B$8*(1-$B$10))/10-$B$4*($B$5*$B$7*(1-B$29)+$B$6*$B$8*(1-$B$10))/10 -> 39.048739 | C30: =$B$4*(1+$A30)*(($B$5+$B$11)*$B$7*(1-C$29)+$B$6*$B$8*(1-$B$10))/10-$B$4*($B$5*$B$7*(1-C$29)+$B$6*$B$8*(1-$B$10))/10 -> 34.58261 | D30: =$B$4*(1+$A30)*(($B$5+$B$11)*$B$7*(1-D$29)+$B$6*$B$8*(1-$B$10))/10-$B$4*($B$5*$B$7*(1-D$29)+$B$6*$B$8*(1-$B$10))/10 -> 30.116481
A31: -0.03 | B31: =$B$4*(1+$A31)*(($B$5+$B$11)*$B$7*(1-B$29)+$B$6*$B$8*(1-$B$10))/10-$B$4*($B$5*$B$7*(1-B$29)+$B$6*$B$8*(1-$B$10))/10 -> -33.821525 | C31: =$B$4*(1+$A31)*(($B$5+$B$11)*$B$7*(1-C$29)+$B$6*$B$8*(1-$B$10))/10-$B$4*($B$5*$B$7*(1-C$29)+$B$6*$B$8*(1-$B$10))/10 -> -34.639267 | D31: =$B$4*(1+$A31)*(($B$5+$B$11)*$B$7*(1-D$29)+$B$6*$B$8*(1-$B$10))/10-$B$4*($B$5*$B$7*(1-D$29)+$B$6*$B$8*(1-$B$10))/10 -> -35.457009
A32: -0.05 | B32: =$B$4*(1+$A32)*(($B$5+$B$11)*$B$7*(1-B$29)+$B$6*$B$8*(1-$B$10))/10-$B$4*($B$5*$B$7*(1-B$29)+$B$6*$B$8*(1-$B$10))/10 -> -106.69179 | C32: =$B$4*(1+$A32)*(($B$5+$B$11)*$B$7*(1-C$29)+$B$6*$B$8*(1-$B$10))/10-$B$4*($B$5*$B$7*(1-C$29)+$B$6*$B$8*(1-$B$10))/10 -> -103.86114 | D32: =$B$4*(1+$A32)*(($B$5+$B$11)*$B$7*(1-D$29)+$B$6*$B$8*(1-$B$10))/10-$B$4*($B$5*$B$7*(1-D$29)+$B$6*$B$8*(1-$B$10))/10 -> -101.0305
